validations_common/__init__.py
validations_common/library/__init__.py
validations_common/library/advanced_format.py
validations_common/library/check_package_update.py
validations_common/library/hiera.py
validations_common/library/reportentry.py
validations_common/library/validations_read_ini.py
validations_common/library/warn.py
validations_common/playbooks/512e.yaml
validations_common/playbooks/check-cpu.yaml
validations_common/playbooks/check-disk-space-pre-upgrade.yaml
validations_common/playbooks/check-disk-space.yaml
validations_common/playbooks/check-ftype.yaml
validations_common/playbooks/check-latest-packages-version.yaml
validations_common/playbooks/check-ram.yaml
validations_common/playbooks/check-rsyslog.yaml
validations_common/playbooks/check-selinux-mode.yaml
validations_common/playbooks/dns.yaml
validations_common/playbooks/no-op.yaml
validations_common/playbooks/ntp.yaml
validations_common/playbooks/service-status.yaml
validations_common/playbooks/validate-selinux.yaml
validations_common/playbooks/verify-package.yaml
validations_common/roles/advanced_format_512e_support/molecule/default/converge.yml
validations_common/roles/advanced_format_512e_support/molecule/default/molecule.yml
validations_common/roles/advanced_format_512e_support/tasks/main.yml
validations_common/roles/check_cpu/defaults/main.yml
validations_common/roles/check_cpu/molecule/default/converge.yml
validations_common/roles/check_cpu/molecule/default/molecule.yml
validations_common/roles/check_cpu/tasks/main.yml
validations_common/roles/check_disk_space/defaults/main.yml
validations_common/roles/check_disk_space/molecule/default/converge.yml
validations_common/roles/check_disk_space/molecule/default/molecule.yml
validations_common/roles/check_disk_space/tasks/main.yml
validations_common/roles/check_latest_packages_version/defaults/main.yml
validations_common/roles/check_latest_packages_version/molecule/default/converge.yml
validations_common-1.9.0.dist-info/AUTHORS
validations_common-1.9.0.dist-info/LICENSE
validations_common-1.9.0.dist-info/METADATA
validations_common-1.9.0.dist-info/WHEEL
validations_common-1.9.0.dist-info/pbr.json
validations_common-1.9.0.dist-info/top_level.txt
validations_common-1.9.0.dist-info/RECORD
